bill_generator/__init__.py
bill_generator/__main__.py
bill_generator/bill_manager.py
bill_generator_super_kolya-0.1.1.dist-info/METADATA
bill_generator_super_kolya-0.1.1.dist-info/WHEEL
bill_generator_super_kolya-0.1.1.dist-info/entry_points.txt
bill_generator_super_kolya-0.1.1.dist-info/top_level.txt
bill_generator_super_kolya-0.1.1.dist-info/RECORD
