Metadata-Version: 2.1
Name: bill_generator_super_kolya
Version: 0.1.1
Summary: Krutoi packege
Author: Nikolai
Author-email: kolaleuhin@gmail.com
